pysteed.cpython-38-x86_64-linux-gnu.so
pysteed-1.0.0.1.dist-info/top_level.txt
pysteed-1.0.0.1.dist-info/LICENSE
pysteed-1.0.0.1.dist-info/METADATA
pysteed-1.0.0.1.dist-info/RECORD
pysteed-1.0.0.1.dist-info/WHEEL
pysteed.libs/liblz4-af1653fb.so.1.8.3
pysteed.libs/libsteed-fbf55948.so
