Metadata-Version: 2.1
Name: pysteed
Version: 1.0.0.1
Summary: Python interface for Steed
Home-page: https://github.com/steed-ict/steed
Author: zhiyiwang
Author-email: wangzhiyi@ict.ac.cn
License-File: LICENSE
